easycoder/__init__.py
easycoder/ec_border.py
easycoder/ec_classes.py
easycoder/ec_compiler.py
easycoder/ec_condition.py
easycoder/ec_core.py
easycoder/ec_gclasses.py
easycoder/ec_graphics.py
easycoder/ec_handler.py
easycoder/ec_keyboard.py
easycoder/ec_mqtt.py
easycoder/ec_program.py
easycoder/ec_psutil.py
easycoder/ec_timestamp.py
easycoder/ec_value.py
easycoder/debugger/__init__.py
easycoder/debugger/ec_dbg_value_display copy.py
easycoder/debugger/ec_dbg_value_display.py
easycoder/debugger/ec_dbg_watch_list copy.py
easycoder/debugger/ec_dbg_watchlist.py
easycoder/debugger/ec_debug.py
easycoder/icons/close.png
easycoder/icons/exit.png
easycoder/icons/run.png
easycoder/icons/step.png
easycoder/icons/stop.png
easycoder/icons/tick.png
easycoder-260201.2.dist-info/entry_points.txt
easycoder-260201.2.dist-info/licenses/LICENSE
easycoder-260201.2.dist-info/WHEEL
easycoder-260201.2.dist-info/METADATA
easycoder-260201.2.dist-info/RECORD
