Metadata-Version: 2.4
Name: easycoder
Version: 260201.2
Summary: Rapid scripting in English
Keywords: compiler,scripting,prototyping,programming,coding,python,low code,hypertalk,computer language,learn to code
Author-email: Graham Trott <gtanyware@gmail.com>
Classifier: License :: OSI Approved :: MIT License
License-File: LICENSE
Requires-Dist: pytz
Requires-Dist: requests
Requires-Dist: psutil
Requires-Dist: paramiko
Requires-Dist: pyside6
Requires-Dist: paho-mqtt
Project-URL: Home, https://github.com/easycoder/easycoder-py
